{
  "_fv": 39,
  "_type": "rangeditem",
  "definition": {
    "renderType": 0,
    "texture": "joseph_egg_caplock_pistol",
    "customModelName": "Normal",
    "name": "Joseph Egg Percussion Pistol",
    "specialInfo": [
      "Single Action: Uses percussion caps",
      "Requires small paper cartidges to Reload."
    ],
    "creativeTab": {
      "value": "CUSTOM:GunsmithCognitisPercussioncapTab"
    },
    "stackSize": 1,
    "ammoItem": {
      "value": ""
    },
    "shootConstantly": false,
    "usageCount": 721,
    "actionSound": {
      "value": "CUSTOM:musket_shot"
    },
    "hasGlow": false,
    "animation": "none",
    "enableMeleeDamage": false,
    "damageVsEntity": 0.0,
    "onRangedItemUsed": {
      "name": "JosephEggPistolItemUsed"
    },
    "useCondition": {
      "name": "JosephEggPistolCanUseRanged"
    },
    "bulletPower": 3.0,
    "bulletDamage": 1.8,
    "bulletKnockback": 0,
    "bulletParticles": false,
    "bulletIgnitesFire": false,
    "bulletItemTexture": {
      "value": "CUSTOM:MusketBallProjectile"
    },
    "bulletModel": "Default",
    "customBulletModelTexture": ""
  }
}